.gitignore
README.md
pyproject.toml
requirements.txt
riscv.pth
setup.cfg
setup.py
libriscv.egg-info/PKG-INFO
libriscv.egg-info/SOURCES.txt
libriscv.egg-info/dependency_links.txt
libriscv.egg-info/requires.txt
libriscv.egg-info/top_level.txt
scripts/pyspike
src/main/cpp/module.cc
src/main/python/libriscv/__init__.py
src/main/python/libriscv/_version.py
tests/__init__.py
tests/test_disasm.py